DingtalkConnectflowSDk/__init__.py
DingtalkConnectflowSDk/_table/_types.py
DingtalkConnectflowSDk/_table/table.py
DingtalkConnectflowSDk/_types.py
DingtalkConnectflowSDk/complex_table.py
xmes_dingtalk_connectflow_sdk-1.0.3.dist-info/LICENSE
xmes_dingtalk_connectflow_sdk-1.0.3.dist-info/METADATA
xmes_dingtalk_connectflow_sdk-1.0.3.dist-info/WHEEL
xmes_dingtalk_connectflow_sdk-1.0.3.dist-info/RECORD
