Metadata-Version: 2.1
Name: xmes-dingtalk-connectflow-sdk
Version: 1.0.3
Summary: DingTalk Connection Platform Connection Flow SDK
License: MIT
Author: leslieliang
Author-email: zwliang98@163.com
Requires-Python: >=3.9
Classifier: License :: OSI Approved :: MIT License
Classifier: Programming Language :: Python :: 3
Classifier: Programming Language :: Python :: 3.9
Classifier: Programming Language :: Python :: 3.10
Classifier: Programming Language :: Python :: 3.11
Classifier: Programming Language :: Python :: 3.12
Requires-Dist: requests (>=2.32.3,<3.0.0)
